cloudflare_exporter/__init__.py
cloudflare_exporter/collector.py
cloudflare_exporter/config.py
cloudflare_exporter/exporter.py
cloudflare_exporter/handlers.py
cloudflare_exporter/lib/__init__.py
cloudflare_exporter/lib/statistics.py
cloudflare_exporter-0.7.data/data/requirements.txt
cloudflare_exporter-0.7.data/data/tests-requirements.txt
cloudflare_exporter-0.7.dist-info/LICENSE
cloudflare_exporter-0.7.dist-info/METADATA
cloudflare_exporter-0.7.dist-info/WHEEL
cloudflare_exporter-0.7.dist-info/entry_points.txt
cloudflare_exporter-0.7.dist-info/top_level.txt
cloudflare_exporter-0.7.dist-info/RECORD
